[
  {
    "product": "Asura",
    "desc" : "Beschreibung",
    "unit": [
      {
        "name": "Q2000",
        "procedures": [
          {
            "procedurname": "UP_Q2000_START:1",
            "procedurdesc": "Setzt die Startparameter zu Beginn des Rezeptes",
            "parameters": [
              {
                "paramName": "FP_APP_SOLE",
                "value": 45,
                "unit": "째C",
                "paramdesc": "Umschalt Punkt der Sole beim R체hrwerk",
                "history": [
                  {
                    "id": 1,
                    "change": "2012-04-23T18:25:43.511Z",
                    "value": 35,
                    "visum": "SL"
                  },
                  {
                    "id": 2,
                    "change": "2012-04-23T16:25:43.511Z",
                    "value": 35,
                    "visum": "SL"
                  }
                ]
              },
              {
                "paramName": "FP_KK_TCW",
                "value": 45,
                "min": -20,
                "max": 100,
                "unit": "째C",
                "paramdesc": "Umschalt Punkt der Sole beim R체hrwerk",
                "history": [
                  {
                    "id": 1,
                    "change": "2012-04-11T18:25:43.511Z",
                    "value": 15,
                    "visum": "SL"
                  },
                  {
                    "id": 2,
                    "change": "2012-02-23T16:25:43.511Z",
                    "value": 25,
                    "visum": "SL"
                  }
                ]
              }
            ]
          }
        ]
      },
      {
        "name": "P105"
      }
    ]
  },
  {
    "product": "Foramsulfuron"
  }
]